{
  "user": {
    "entities": {
      "string": {
        "id": string,
        "name": string
      }
    }
  },
  "post": {
    "entities": {
      "string": {
        "id": string,
        "userId": string,
        "text": string
      }
    }
  },
  "like": {
    "entities": {
      "string": {
        "id": string,
        "userId": string,
        "postId": string
      }
    }
  },
  "subscription": {
    "entities": {
      "string": {
        "id": string,
        "fromUserId": string, // айди того кто подписался
        "toUserId": string // айди того на кого подписались
      }
    }
  }
}
